win_defender/__init__.py
win_defender/tools.py
win_defender/utils.py
win_defender-0.2.0.dist-info/LICENSE
win_defender-0.2.0.dist-info/METADATA
win_defender-0.2.0.dist-info/WHEEL
win_defender-0.2.0.dist-info/RECORD
